sentiment/__init__.py
sentiment_analysis-0.1.5.dist-info/LICENSE
sentiment_analysis-0.1.5.dist-info/METADATA
sentiment_analysis-0.1.5.dist-info/WHEEL
sentiment_analysis-0.1.5.dist-info/top_level.txt
sentiment_analysis-0.1.5.dist-info/RECORD
