Metadata-Version: 2.1
Name: sentiment-analysis
Version: 0.1.5
Summary: Sentiment analysis for paragraph or sentence
Home-page: https://github.com/Mysterico/sentiment_analysis
Author: Philip Kim
Author-email: philip@mysterico.com
License: MIT
Keywords: nlp,korean
Platform: UNKNOWN
Classifier: Programming Language :: Python :: 3
Classifier: Programming Language :: Python :: 3.2
Classifier: Programming Language :: Python :: 3.3
Classifier: Programming Language :: Python :: 3.4
Classifier: Programming Language :: Python :: 3.5
Classifier: Programming Language :: Python :: 3.6
Classifier: Programming Language :: Python :: 3.7
Requires-Python: >=3
Requires-Dist: konlpy
Requires-Dist: lexrankr
Requires-Dist: tensorflow
Requires-Dist: numpy
Requires-Dist: pandas
Requires-Dist: nltk
Requires-Dist: langdetect
